{
  "spec": "Hologram OS mobile appearance (Dark · Light · Immersive) is ONE canonical axis on the holo-theme.js engine (holo.theme.v1), applied before first paint by a synchronous bootstrap across the boot chain (splash · shell), with one launcher-clean modal primitive (window.HoloSheet on native <dialog>) that honors the 48px tap floor and 16px readability floor. The homepage (index.html) is never edited; its legacy choice is migrated once. New served modules are content-addressed in os-closure (Law L5).",
  "authority": "ADR-0030 (Holo UI façade) · ADR-0057 (minimum text size) · CSS Color Adjustment L1 (light-dark()) · W3C Custom Properties + @property · HTML <dialog> · WCAG 2.2 (2.5.8 target size) · Material Design 3 · holospaces Law L5 · verify by static analysis of the served engine + boot chain + closure",
  "witnessed": true,
  "covers": [
    "mobile-appearance",
    "themes",
    "dark-light-immersive",
    "pre-paint-bootstrap",
    "holo-sheet",
    "immersive-backdrop",
    "curated-wallpapers",
    "login-picker",
    "appearance-picker",
    "tap-floor",
    "font-min",
    "canonical-axis",
    "conformance"
  ],
  "floor": 16,
  "checks": {
    "holo-theme.js state declares the immersive axis (immersive + wallpaper)": true,
    "apply() publishes data-holo-immersive on <html>": true,
    "apply() publishes --holo-wallpaper": true,
    "κ wallpaper resolves to the serverless /.holo store (L5)": true,
    "engine exports setMode / setImmersive / setWallpaper": true,
    "pre-paint bootstrap (holo-appearance-boot.js) exists": true,
    "bootstrap reads the canonical holo.theme.v1 state": true,
    "bootstrap pins data-holo-palette + color-scheme before paint": true,
    "bootstrap pins data-holo-immersive before paint": true,
    "bootstrap migrates the homepage legacy key (index.html untouched)": true,
    "splash.html loads the bootstrap as a synchronous script": true,
    "shell.html loads the bootstrap as a synchronous script": true,
    "holo-sheet.js exposes window.HoloSheet": true,
    "HoloSheet is built on the native <dialog> (focus-trap / Esc / top-layer)": true,
    "HoloSheet honors the ≥48px tap floor (--holo-tap)": true,
    "HoloSheet is token-driven (wears the active palette/immersive theme)": true,
    "HoloSheet renders no sub-16px text": true,
    "shell.html loads holo-sheet.js": true,
    "shell has the immersive backdrop layer (#immersive-wall)": true,
    "Immersive paints the engine's chosen wallpaper (--holo-wallpaper)": true,
    "Immersive is an OVERLAY — the desktop keeps its content-addressed gallery wallpaper (no forced hide)": true,
    "curated Immersive set is κ-sealed and re-derives (L5)": true,
    "curated Immersive set is attributed (Unsplash license)": true,
    "login pre-paints the appearance via the bootstrap": true,
    "login offers a Dark/Light/Immersive toggle that persists to holo.theme.v1": true,
    "login reflects the chosen palette (a real Light theme, not only Dark)": true,
    "shell exposes an Appearance picker over the curated set": true,
    "HoloSheet supports thumbnail options (the wallpaper chooser)": true,
    "holo-appearance-boot.js is κ-pinned in os-closure": true,
    "holo-sheet.js is κ-pinned in os-closure": true
  },
  "curated": {
    "count": 5,
    "verified": 5,
    "attributed": true
  },
  "subFloor": []
}
